MANIFEST.in
README.md
setup.cfg
setup.py
config/rete.yml
config/rete_schema.yml
data/chrome.json
data/pulseaudio.client.conf
rete/VERSION
rete/__init__.py
rete/__main__.py
rete/cli.py
rete/utils.py
rete.egg-info/PKG-INFO
rete.egg-info/SOURCES.txt
rete.egg-info/dependency_links.txt
rete.egg-info/entry_points.txt
rete.egg-info/requires.txt
rete.egg-info/top_level.txt
rete/iptables/lan_rules.v4
rete/iptables/lan_rules.v6
rete/iptables/rules.v4
rete/iptables/rules.v6