Metadata-Version: 2.1
Name: rete
Version: 1.0.15
Summary: UNKNOWN
Home-page: UNKNOWN
Author: retenet
Author-email: dev@exploit.design
License: GPLv3
Keywords: browser
Platform: UNKNOWN
Classifier: Development Status :: 3 - Alpha
Classifier: Intended Audience :: End Users/Desktop
Classifier: License :: OSI Approved :: MIT License
Classifier: Programming Language :: Python :: 3
Classifier: Operating System :: POSIX :: Linux
Classifier: Environment :: Console
Provides-Extra: dev
